README.md
generate_certs.py
setup.py
govroam_certificate_cli.egg-info/PKG-INFO
govroam_certificate_cli.egg-info/SOURCES.txt
govroam_certificate_cli.egg-info/dependency_links.txt
govroam_certificate_cli.egg-info/requires.txt
govroam_certificate_cli.egg-info/top_level.txt