Metadata-Version: 2.1
Name: govroam-certificate-cli
Version: 1.1
Summary: CLI certificate generator for Govroam
Home-page: UNKNOWN
Author: Mike Richardson
Author-email: doctor@perpetual.name
License: UNKNOWN
Platform: UNKNOWN
Classifier: Programming Language :: Python :: 2
Classifier: License :: OSI Approved :: MIT License
Classifier: Operating System :: OS Independent
